CoinWebsock
