Metadata-Version: 1.1
Name: CoinWebsock
Version: 1.3.3
Summary: Asyncronous Python REST and WebSocket Clients for the Coinbase Pro virtual currency trading platform.
Home-page: https://github.com/Nathan5095/CoinWebsock
Author: Nathan Clegg
Author-email: Nathan_5095@yahoo.com
License: MIT license
Keywords: copra coinbase pro gdax api bitcoin litecoin etherium rest websocket client
Platform: UNKNOWN
Classifier: Development Status :: 5 - Production/Stable
Classifier: Intended Audience :: Developers
Classifier: License :: OSI Approved :: MIT License
Classifier: Natural Language :: English
Classifier: Programming Language :: Python :: 3
Classifier: Programming Language :: Python :: 3.5
Classifier: Programming Language :: Python :: 3.6
